LICENSE
model_class/__init__.py
model_class-0.1.0.dist-info/LICENSE
model_class-0.1.0.dist-info/WHEEL
model_class-0.1.0.dist-info/METADATA
model_class-0.1.0.dist-info/RECORD
